ldbg_jsonrpc/__init__.py
ldbg_jsonrpc/client.py
ldbg_jsonrpc-1.0.1.dist-info/LICENSE
ldbg_jsonrpc-1.0.1.dist-info/METADATA
ldbg_jsonrpc-1.0.1.dist-info/WHEEL
ldbg_jsonrpc-1.0.1.dist-info/top_level.txt
ldbg_jsonrpc-1.0.1.dist-info/RECORD
